MDSimsEval/AnalysisActorClass.py
MDSimsEval/__init__.py
MDSimsEval/pca_analysis.py
MDSimsEval/rg_sasa_analysis.py
MDSimsEval/rmsf_analysis.py
MDSimsEval/rmsf_baseline_models.py
MDSimsEval/rmsf_bootstrapped_analysis.py
MDSimsEval/utils.py
mdsimseval-0.1.1.dist-info/LICENSE
mdsimseval-0.1.1.dist-info/WHEEL
mdsimseval-0.1.1.dist-info/METADATA
mdsimseval-0.1.1.dist-info/RECORD
