Metadata-Version: 2.1
Name: mdsimseval
Version: 0.1.1
Summary: Collective analysis on a set of Molecular Dynamics simulations.
Home-page: https://mikexydas.github.io/MDSimsEval/
License: MIT
Keywords: molecular-dynamics,RMSF
Author: Mike Xydas
Author-email: mikexydas@gmail.com
Requires-Python: >=3.6.9,<4.0.0
Classifier: License :: OSI Approved :: MIT License
Classifier: Programming Language :: Python :: 3
Classifier: Programming Language :: Python :: 3.7
Classifier: Programming Language :: Python :: 3.8
Classifier: Programming Language :: Python :: 3.9
Requires-Dist: MDAnalysis (>=1.0.0,<2.0.0)
Requires-Dist: imgkit (>=1.0.2,<2.0.0)
Requires-Dist: matplotlib (>=3.3.2,<4.0.0)
Requires-Dist: mdtraj (>=1.9.4,<2.0.0)
Requires-Dist: numpy (>=1.19.2,<2.0.0)
Requires-Dist: pandas (>=1.0.3,<2.0.0)
Requires-Dist: scikit-learn (>=0.23.2,<0.24.0)
Requires-Dist: scipy (>=1.5.2,<2.0.0)
Requires-Dist: seaborn (>=0.11.0,<0.12.0)
Requires-Dist: tqdm (>=4.50.2,<5.0.0)
Project-URL: Repository, https://github.com/MikeXydas/MDSimsEval
